rkguinew/__init__.py
rkguinew/rk.py
rkguinew/rrk.py
rkguinew-0.1.2.dist-info/METADATA
rkguinew-0.1.2.dist-info/WHEEL
rkguinew-0.1.2.dist-info/top_level.txt
rkguinew-0.1.2.dist-info/RECORD
